football/__init__.py
football/constants.py
football/football.py
football/utils.py
football/models/__init__.py
football/models/competition.py
football/models/fixture.py
football/models/player.py
football/models/table.py
football/models/team.py
football-0.2.0.dist-info/LICENSE.txt
football-0.2.0.dist-info/METADATA
football-0.2.0.dist-info/RECORD
football-0.2.0.dist-info/WHEEL
football-0.2.0.dist-info/top_level.txt
